[
  {
    "name": "Guirlanda de Páscoa",
    "description": "Guirlanda decorativa com coelhos e flores em feltro.",
    "image": "/src/assets/images/products/img1.jpeg",
    "price": 85.9,
    "type": "Promoção",
    "spanType": "spanPromo",
    "prevPrice": 99.9
  },
  {
    "name": "Pano de Prato Bordado",
    "description": "Pano de prato com bordado em patchwork de galinhas.",
    "image": "/src/assets/images/products/img2.jpeg",
    "price": 25.0,
    "type": "Mais vendido",
    "spanType": "spanTopSell",
    "prevPrice": 0
  },
  {
    "name": "Coelho de Enfeite",
    "description": "Coelho de tecido com laço xadrez, ideal para decoração de Páscoa.",
    "image": "/src/assets/images/products/img3.jpeg",
    "price": 45.0,
    "type": "Novo",
    "spanType": "spanNew",
    "prevPrice": 0
  },
  {
    "name": "Centro de Mesa Patchwork",
    "description": "Centro de mesa feito à mão com tecidos em tons pastel.",
    "image": "/src/assets/images/products/img4.jpeg",
    "price": 60.0,
    "type": "",
    "spanType": "",
    "prevPrice": 0
  },
  {
    "name": "Almofada Patchwork",
    "description": "Almofada artesanal com aplicação de corações.",
    "image": "/src/assets/images/products/img5.jpeg",
    "price": 55.0,
    "type": "Promoção",
    "spanType": "spanPromo",
    "prevPrice": 65.0
  },
  {
    "name": "Guirlanda Natalina",
    "description": "Guirlanda feita com tecidos natalinos e enfeites dourados.",
    "image": "/src/assets/images/products/img6.jpeg",
    "price": 95.0,
    "type": "Mais vendido",
    "spanType": "spanTopSell",
    "prevPrice": 0
  },
  {
    "name": "Puxa-Saco Patchwork",
    "description": "Organizador de sacos plásticos com estampa floral.",
    "image": "/src/assets/images/products/img7.jpeg",
    "price": 30.0,
    "type": "Novo",
    "spanType": "spanNew",
    "prevPrice": 0
  },
  {
    "name": "Jogo Americano Patchwork",
    "description": "Conjunto com 4 jogos americanos coloridos.",
    "image": "/src/assets/images/products/img8.jpeg",
    "price": 70.0,
    "type": "Promoção",
    "spanType": "spanPromo",
    "prevPrice": 80.0
  },
  {
    "name": "Guirlanda de Passarinhos",
    "description": "Guirlanda artesanal com passarinhos em feltro.",
    "image": "/src/assets/images/products/img9.jpeg",
    "price": 89.9,
    "type": "",
    "spanType": "",
    "prevPrice": 0
  },
  {
    "name": "Coelho de Pelúcia Artesanal",
    "description": "Coelho feito à mão com tecido macio e acabamento delicado.",
    "image": "/src/assets/images/products/img1.jpeg",
    "price": 50.0,
    "type": "Mais vendido",
    "spanType": "spanTopSell",
    "prevPrice": 0
  },
  {
    "name": "Toalha de Mesa Patchwork",
    "description": "Toalha artesanal com estampas variadas e acabamento bordado.",
    "image": "/src/assets/images/products/img2.jpeg",
    "price": 120.0,
    "type": "Novo",
    "spanType": "spanNew",
    "prevPrice": 0
  },
  {
    "name": "Guirlanda Infantil",
    "description": "Guirlanda personalizada com nome e bichinhos de feltro.",
    "image": "/src/assets/images/products/img3.jpeg",
    "price": 110.0,
    "type": "Promoção",
    "spanType": "spanPromo",
    "prevPrice": 125.0
  },
  {
    "name": "Pano de Prato com Barrado",
    "description": "Pano de prato com barrado de crochê e aplicações florais.",
    "image": "/src/assets/images/products/img4.jpeg",
    "price": 29.9,
    "type": "",
    "spanType": "",
    "prevPrice": 0
  },
  {
    "name": "Guirlanda de Outono",
    "description": "Guirlanda com folhas secas e mini abóboras de tecido.",
    "image": "/src/assets/images/products/img5.jpeg",
    "price": 95.0,
    "type": "Mais vendido",
    "spanType": "spanTopSell",
    "prevPrice": 0
  },
  {
    "name": "Caminho de Mesa Patchwork",
    "description": "Caminho de mesa colorido e costurado à mão.",
    "image": "/src/assets/images/products/img6.jpeg",
    "price": 80.0,
    "type": "Promoção",
    "spanType": "spanPromo",
    "prevPrice": 95.0
  },
  {
    "name": "Coelho de Madeira",
    "description": "Coelho artesanal em madeira pintada à mão.",
    "image": "/src/assets/images/products/img7.jpeg",
    "price": 65.0,
    "type": "Novo",
    "spanType": "spanNew",
    "prevPrice": 0
  },
  {
    "name": "Jogo de Panos de Prato",
    "description": "Kit com 3 panos de prato bordados.",
    "image": "/src/assets/images/products/img8.jpeg",
    "price": 75.0,
    "type": "Mais vendido",
    "spanType": "spanTopSell",
    "prevPrice": 0
  },
  {
    "name": "Guirlanda de Bebê",
    "description": "Guirlanda delicada com nome personalizado e bichinhos fofos.",
    "image": "/src/assets/images/products/img9.jpeg",
    "price": 105.0,
    "type": "",
    "spanType": "",
    "prevPrice": 0
  },
  {
    "name": "Capa de Almofada Patchwork",
    "description": "Capa de almofada com retalhos de tecido coloridos.",
    "image": "/src/assets/images/products/img1.jpeg",
    "price": 40.0,
    "type": "Promoção",
    "spanType": "spanPromo",
    "prevPrice": 50.0
  },
  {
    "name": "Coelho com Cestinha",
    "description": "Coelho de tecido segurando uma cestinha de chocolates.",
    "image": "/src/assets/images/products/img1.jpeg",
    "price": 55.0,
    "type": "Mais vendido",
    "spanType": "spanTopSell",
    "prevPrice": 0
  }
]
